abc_classification/__init__.py
abc_classification/abc_classifier.py
abc_classification/abc_visualiser.py
tests/__init__.py
tests/test_abc_classifier.py
abc_classification-0.8.dist-info/METADATA
abc_classification-0.8.dist-info/WHEEL
abc_classification-0.8.dist-info/top_level.txt
abc_classification-0.8.dist-info/RECORD
