Metadata-Version: 2.1
Name: abc-classification
Version: 0.8
Summary: A package for ABC classification
Home-page: https://github.com/MelikbekyanAshot/abc-classification
Author: Ashot Melikbekyan
Author-email: melikbekyan.ashot@yandex.ru
License: UNKNOWN
Platform: UNKNOWN
Classifier: Programming Language :: Python :: 3.8
Classifier: License :: OSI Approved :: GNU General Public License v3 (GPLv3)
Requires-Dist: pandas
Requires-Dist: numpy
